file_hash/__init__.py
file_hash/__main__.py
file_hash/algorithm.py
file_hash/filter.py
file_hash/func.py
file_hash/hash.py
file_hash/report.py
file_hash/serialize.py
file_hash/worker.py
file_hash-1.0.1.dist-info/METADATA
file_hash-1.0.1.dist-info/RECORD
file_hash-1.0.1.dist-info/WHEEL
file_hash-1.0.1.dist-info/entry_points.txt
file_hash-1.0.1.dist-info/top_level.txt
