Metadata-Version: 2.1
Name: file-hash
Version: 1.0.1
Summary: Simple hashing script for files.
Home-page: https://git.joshuaavalon.io/joshuaavalon/file_hash
Author: Joshua Avalon
License: UNKNOWN
Project-URL: Bug Tracker, https://github.com/joshuaavalon/file_hash
Project-URL: Documentation, https://git.joshuaavalon.io/joshuaavalon/file_hash/blob/master/README.md
Project-URL: Source Code, https://git.joshuaavalon.io/joshuaavalon/file_hash
Platform: UNKNOWN
Classifier: Programming Language :: Python :: 3
Classifier: Programming Language :: Python :: 3 :: Only
Classifier: Programming Language :: Python :: 3.7
Classifier: License :: OSI Approved :: Apache Software License
Classifier: Operating System :: OS Independent
Requires-Python: >=3.7
Requires-Dist: Jinja2 (==2.10)
